vurf/__init__.py
vurf/cli.py
vurf/constants.py
vurf/defaults/config.toml
vurf/defaults/packages.vurf
vurf/lib.py
vurf/module.py
vurf/nodes.py
vurf/parser/__init__.py
vurf/parser/indenter.py
vurf/parser/stand_alone.py
vurf/parser/transformer.py
vurf/types.py
vurf_completions/completions.bash
vurf_completions/completions.fish
vurf_completions/completions.zsh
vurf-2.0.0.dist-info/entry_points.txt
vurf-2.0.0.dist-info/LICENSE
vurf-2.0.0.dist-info/WHEEL
vurf-2.0.0.dist-info/METADATA
vurf-2.0.0.dist-info/RECORD
