Metadata-Version: 2.1
Name: vurf
Version: 2.0.0
Summary: Viliam's Universal Requirements Format
Home-page: https://github.com/ViliamV/vurf
License: MIT
Author: Viliam Valent
Author-email: vurf@valent.email
Requires-Python: >=3.8,<4.0
Classifier: License :: OSI Approved :: MIT License
Classifier: Programming Language :: Python :: 3
Classifier: Programming Language :: Python :: 3.10
Classifier: Programming Language :: Python :: 3.8
Classifier: Programming Language :: Python :: 3.9
Requires-Dist: click (>=8.0.0,<9.0.0)
Requires-Dist: tomli (<3.0.0)
Project-URL: Repository, https://github.com/ViliamV/vurf
